[    
    {
        "title":"Front Lever",
        "description1":"How to do front lever in 10 days series blog.Follow my workout plan and progression of front lever and unlock hidden power and skill.",
        "description":"Also follow me on Instagram for daily updates and diet which i am following to achive it.",
        "buttonText":"Front Lever",
        "btnlink":"https://mohitkhyalia.blogspot.com/2025/02/10-day-front-lever-challenge-mastering.html"
    },
    {"title":"Pistol Squat",
      "description1":"Complete guid for pistol squat,click below button to read full blog",
      "buttonText":"Here",
        "btnlink":"https://mohitkhyalia.blogspot.com/2025/02/pistol-squat-progression-step-by-step.html"
    },
    {"title":"Blog",
      "description1":"Checkout my blogs ",
        "buttonText":"Here",
        "btnlink":"https://mohitkhyalia.blogspot.com/"
    }
]
